nexaflops_sdk/__init__.py
nexaflops_sdk/_version.py
nexaflops_sdk/client.py
nexaflops_sdk/exceptions.py
nexaflops_sdk/fingerprint.py
nexaflops_sdk/licenses.py
nexaflops_sdk/models.py
nexaflops_sdk-0.1.0.dist-info/METADATA
nexaflops_sdk-0.1.0.dist-info/WHEEL
nexaflops_sdk-0.1.0.dist-info/RECORD
