Metadata-Version: 2.4
Name: nexaflops-sdk
Version: 0.1.0
Summary: Python SDK for NEXAFLOPS Control Plane API
Project-URL: Homepage, https://nexaflops.io
Project-URL: Documentation, https://docs.nexaflops.io/sdk/python
Project-URL: Repository, https://github.com/vibeswithkk/NEXAFLOPS
Project-URL: Issues, https://github.com/vibeswithkk/NEXAFLOPS/issues
Author-email: NEXAFLOPS Project <sdk@nexaflops.io>
License-Expression: MIT
Keywords: api,license,ml,nexaflops,sdk
Classifier: Development Status :: 4 - Beta
Classifier: Intended Audience :: Developers
Classifier: License :: OSI Approved :: MIT License
Classifier: Operating System :: OS Independent
Classifier: Programming Language :: Python :: 3
Classifier: Programming Language :: Python :: 3.9
Classifier: Programming Language :: Python :: 3.10
Classifier: Programming Language :: Python :: 3.11
Classifier: Programming Language :: Python :: 3.12
Classifier: Topic :: Software Development :: Libraries :: Python Modules
Classifier: Typing :: Typed
Requires-Python: >=3.9
Requires-Dist: httpx>=0.25.0
Requires-Dist: pydantic>=2.0.0
Provides-Extra: dev
Requires-Dist: mypy>=1.0.0; extra == 'dev'
Requires-Dist: pytest-asyncio>=0.21.0; extra == 'dev'
Requires-Dist: pytest>=7.0.0; extra == 'dev'
Requires-Dist: respx>=0.20.0; extra == 'dev'
Requires-Dist: ruff>=0.1.0; extra == 'dev'
